avs_rvtools_analyzer/__init__.py
avs_rvtools_analyzer/config.py
avs_rvtools_analyzer/decorators.py
avs_rvtools_analyzer/helpers.py
avs_rvtools_analyzer/main.py
avs_rvtools_analyzer/models.py
avs_rvtools_analyzer/risk_detection.py
avs_rvtools_analyzer/utils.py
avs_rvtools_analyzer/core/__init__.py
avs_rvtools_analyzer/core/error_handlers.py
avs_rvtools_analyzer/core/exceptions.py
avs_rvtools_analyzer/prompts/risk_analysis_prompt.md
avs_rvtools_analyzer/routes/__init__.py
avs_rvtools_analyzer/routes/api_routes.py
avs_rvtools_analyzer/routes/web_routes.py
avs_rvtools_analyzer/services/__init__.py
avs_rvtools_analyzer/services/analysis_service.py
avs_rvtools_analyzer/services/azure_openai_service.py
avs_rvtools_analyzer/services/file_service.py
avs_rvtools_analyzer/services/sku_service.py
avs_rvtools_analyzer/static/sku.json
avs_rvtools_analyzer/templates/analyze.html
avs_rvtools_analyzer/templates/base.html
avs_rvtools_analyzer/templates/error.html
avs_rvtools_analyzer/templates/explore.html
avs_rvtools_analyzer/templates/index.html
avs_rvtools_analyzer-2026.1.1.dist-info/METADATA
avs_rvtools_analyzer-2026.1.1.dist-info/WHEEL
avs_rvtools_analyzer-2026.1.1.dist-info/entry_points.txt
avs_rvtools_analyzer-2026.1.1.dist-info/RECORD
