Metadata-Version: 2.4
Name: avs-rvtools-analyzer
Version: 2026.1.1
Summary: A tool for analyzing RVTools data.
Author-email: Ludovic Rivallain <ludovic.rivallain+pip@gmail.com>
Requires-Python: >=3.12
Requires-Dist: fastapi
Requires-Dist: fastmcp
Requires-Dist: flask
Requires-Dist: jinja2
Requires-Dist: openai
Requires-Dist: openpyxl
Requires-Dist: pandas
Requires-Dist: python-dotenv
Requires-Dist: python-multipart
Requires-Dist: uvicorn[standard]
Requires-Dist: xlrd
Provides-Extra: dev
Requires-Dist: black; extra == 'dev'
Requires-Dist: flake8; extra == 'dev'
Requires-Dist: isort; extra == 'dev'
Requires-Dist: pytest; extra == 'dev'
Requires-Dist: pytest-cov; extra == 'dev'
Requires-Dist: pytest-flask; extra == 'dev'
